cgpt/__init__.py
cgpt/__main__.py
cgpt/app/__init__.py
cgpt/app/base.py
cgpt/app/client/__init__.py
cgpt/app/client/main.py
cgpt/app/commands/__init__.py
cgpt/app/commands/main.py
cgpt/app/create_env.py
cgpt/app/main.py
cgpt/app/plugin.py
cgpt/app/server/__init__.py
cgpt/app/server/main.py
cgpt/app/utils/__init__.py
cgpt/app/utils/constant.py
cgpt/app/utils/verify_env.py
cgpt/py.typed
cgpt-1.2.11.dist-info/LICENSE
cgpt-1.2.11.dist-info/METADATA
cgpt-1.2.11.dist-info/WHEEL
cgpt-1.2.11.dist-info/entry_points.txt
cgpt-1.2.11.dist-info/RECORD
