Metadata-Version: 2.1
Name: cgpt
Version: 1.2.11
Summary: Cgpt
Home-page: https://github.com/ainayves/cgpt
License: MIT
Author: Aina Yves
Author-email: randrianaina.yves@gmail.com
Requires-Python: >=3.10,<4.0
Classifier: Development Status :: 5 - Production/Stable
Classifier: License :: OSI Approved :: MIT License
Classifier: Programming Language :: Python :: 3
Classifier: Programming Language :: Python :: 3.10
Classifier: Programming Language :: Python :: 3.11
Classifier: Programming Language :: Python :: 3.12
Requires-Dist: click (>=8.0.1)
Requires-Dist: openai (>=0.28,<0.29)
Requires-Dist: python-dotenv
Requires-Dist: termcolor
Project-URL: Changelog, https://github.com/ainayves/cgpt/releases
Project-URL: Documentation, https://cgpt.readthedocs.io
Project-URL: Repository, https://github.com/ainayves/cgpt
